app/__init__.py
app/analysis.py
app/client.py
app/errors.py
app/utils.py
conductor_api/__init__.py
conductor_api/analysis.py
conductor_api/client.py
conductor_api/errors.py
conductor_api/utils.py
tests/__init__.py
tests/conftest.py
tests/integration/__init__.py
tests/integration/client_integration_test.py
tests/unit/__init__.py
tests/unit/analysis_test.py
tests/unit/client_test.py
tests/unit/utils_test.py
conductor_api-2.1.0.dist-info/LICENSE
conductor_api-2.1.0.dist-info/METADATA
conductor_api-2.1.0.dist-info/WHEEL
conductor_api-2.1.0.dist-info/top_level.txt
conductor_api-2.1.0.dist-info/RECORD
