Metadata-Version: 2.1
Name: conductor-api
Version: 2.1.0
Summary: A client to assist in connecting with the Conductor API
Home-page: https://github.com/Conductor/searchlight-api-client-python
Author: Dan Goodman
Author-email: dgoodman@conductor.com
License: Apache 2.0
Requires-Python: >=3.8
License-File: LICENSE
Requires-Dist: requests >=2.19.1
Provides-Extra: dev
Requires-Dist: pytest ==7.4.3 ; extra == 'dev'
Requires-Dist: pytest-cov ==4.1.0 ; extra == 'dev'
Requires-Dist: flake8 ==6.1.0 ; extra == 'dev'
